{
  "project_info": {
    "project_number": "517620440641",
    "firebase_url": "https://assigment7-c359f-default-rtdb.europe-west1.firebasedatabase.app",
    "project_id": "assigment7-c359f",
    "storage_bucket": "assigment7-c359f.firebasestorage.app"
  },
  "client": [
    {
      "client_info": {
        "mobilesdk_app_id": "1:517620440641:android:d78e444a292d2001f5f0c0",
        "android_client_info": {
          "package_name": "com.example.cross"
        }
      },
      "oauth_client": [
        {
          "client_id": "517620440641-8bjtfg0gtp8quu8qhqh62apppa8v449u.apps.googleusercontent.com",
          "client_type": 3
        }
      ],
      "api_key": [
        {
          "current_key": "AIzaSyCwRg6BLV8XeYS28APFYxi-TL8CT_FWM4M"
        }
      ],
      "services": {
        "appinvite_service": {
          "other_platform_oauth_client": [
            {
              "client_id": "517620440641-8bjtfg0gtp8quu8qhqh62apppa8v449u.apps.googleusercontent.com",
              "client_type": 3
            },
            {
              "client_id": "517620440641-c0qrslng0saejch93q09igk8jgvdg7tg.apps.googleusercontent.com",
              "client_type": 2,
              "ios_info": {
                "bundle_id": "com.example.cross"
              }
            }
          ]
        }
      }
    }
  ],
  "configuration_version": "1"
}